{"cameraMode":{"drawMode":0,"name":"Shaded","section":"Shading Mode"},"sceneLighting":true,"audioPlay":false,"sceneViewState":{"m_AlwaysRefresh":false,"showFog":true,"showSkybox":true,"showFlares":true,"showImageEffects":true,"showParticleSystems":true,"showVisualEffectGraphs":true,"m_FxEnabled":true},"in2DMode":false,"pivot":{"x":0.4858724772930145,"y":-0.6853042840957642,"z":-4.69461727142334},"rotation":{"x":-0.0018098901491612197,"y":-0.012902473099529744,"z":0.000023183689336292446,"w":-0.999919056892395},"size":3.42403507232666,"orthographic":false}